pycounts_jd25/__init__.py
pycounts_jd25/plotting.py
pycounts_jd25/pycounts_jd25.py
pycounts_jd25-0.2.0.dist-info/LICENSE
pycounts_jd25-0.2.0.dist-info/METADATA
pycounts_jd25-0.2.0.dist-info/WHEEL
pycounts_jd25-0.2.0.dist-info/RECORD
