Metadata-Version: 2.3
Name: pycounts_jd25
Version: 0.2.0
Summary: Calculate word counts in a text file and plot word counts
License: MIT
Author: Julian Daduica
Requires-Python: >=3.10
Classifier: License :: OSI Approved :: MIT License
Classifier: Programming Language :: Python :: 3
Classifier: Programming Language :: Python :: 3.10
Classifier: Programming Language :: Python :: 3.11
Classifier: Programming Language :: Python :: 3.12
Classifier: Programming Language :: Python :: 3.13
Requires-Dist: matplotlib (>=3.4.3)
Requires-Dist: numpy (>=2.2.1,<3.0.0)
